[
    {
        "id": "wx56YbVLVzg",
        "created_at": "2020-08-11T01:18:58-04:00",
        "updated_at": "2021-12-12T01:12:54-05:00",
        "promoted_at": null,
        "width": 3888,
        "height": 2592,
        "color": "#40598c",
        "blur_hash": "LAAdj1EA9F$v0[R2w?S*ks%1s,aK",
        "description": "Mexican Straw Grass growing under the blazing Arizona sun",
        "alt_description": "brown grass under blue sky during daytime",
        "urls": {
            "raw": "https://images.unsplash.com/photo-1597123078458-ab18bf6bda4a?ixid=MnwyODE0NDJ8MHwxfHNlYXJjaHwxfHxkZWZpYW50fGVufDB8MHx8fDE2MzkzNTEyOTA&ixlib=rb-1.2.1",
            "full": "https://images.unsplash.com/photo-1597123078458-ab18bf6bda4a?crop=entropy&cs=srgb&fm=jpg&ixid=MnwyODE0NDJ8MHwxfHNlYXJjaHwxfHxkZWZpYW50fGVufDB8MHx8fDE2MzkzNTEyOTA&ixlib=rb-1.2.1&q=85",
            "regular": "https://images.unsplash.com/photo-1597123078458-ab18bf6bda4a?crop=entropy&cs=tinysrgb&fit=max&fm=jpg&ixid=MnwyODE0NDJ8MHwxfHNlYXJjaHwxfHxkZWZpYW50fGVufDB8MHx8fDE2MzkzNTEyOTA&ixlib=rb-1.2.1&q=80&w=1080",
            "small": "https://images.unsplash.com/photo-1597123078458-ab18bf6bda4a?crop=entropy&cs=tinysrgb&fit=max&fm=jpg&ixid=MnwyODE0NDJ8MHwxfHNlYXJjaHwxfHxkZWZpYW50fGVufDB8MHx8fDE2MzkzNTEyOTA&ixlib=rb-1.2.1&q=80&w=400",
            "thumb": "https://images.unsplash.com/photo-1597123078458-ab18bf6bda4a?crop=entropy&cs=tinysrgb&fit=max&fm=jpg&ixid=MnwyODE0NDJ8MHwxfHNlYXJjaHwxfHxkZWZpYW50fGVufDB8MHx8fDE2MzkzNTEyOTA&ixlib=rb-1.2.1&q=80&w=200"
        },
        "links": {
            "self": "https://api.unsplash.com/photos/wx56YbVLVzg",
            "html": "https://unsplash.com/photos/wx56YbVLVzg",
            "download": "https://unsplash.com/photos/wx56YbVLVzg/download?ixid=MnwyODE0NDJ8MHwxfHNlYXJjaHwxfHxkZWZpYW50fGVufDB8MHx8fDE2MzkzNTEyOTA",
            "download_location": "https://api.unsplash.com/photos/wx56YbVLVzg/download?ixid=MnwyODE0NDJ8MHwxfHNlYXJjaHwxfHxkZWZpYW50fGVufDB8MHx8fDE2MzkzNTEyOTA"
        },
        "categories": [],
        "likes": 9,
        "liked_by_user": false,
        "current_user_collections": [],
        "sponsorship": null,
        "topic_submissions": {},
        "user": {
            "id": "yxEMRFosME8",
            "updated_at": "2021-12-12T08:50:19-05:00",
            "username": "jancanty",
            "name": "Jan Canty",
            "first_name": "Jan",
            "last_name": "Canty",
            "twitter_username": null,
            "portfolio_url": null,
            "bio": "Psychologist, podcast host (Domino Effect of Murder) and author (A Life Divided.) Photography helped me teach cross-cultural psychotherapy, which is why I traveled.  I garden too and tried to emulate the beauty I saw in Guatemala.\r\n",
            "location": null,
            "links": {
                "self": "https://api.unsplash.com/users/jancanty",
                "html": "https://unsplash.com/@jancanty",
                "photos": "https://api.unsplash.com/users/jancanty/photos",
                "likes": "https://api.unsplash.com/users/jancanty/likes",
                "portfolio": "https://api.unsplash.com/users/jancanty/portfolio",
                "following": "https://api.unsplash.com/users/jancanty/following",
                "followers": "https://api.unsplash.com/users/jancanty/followers"
            },
            "profile_image": {
                "small": "https://images.unsplash.com/profile-1590013010768-2c020b66411aimage?ixlib=rb-1.2.1&q=80&fm=jpg&crop=faces&cs=tinysrgb&fit=crop&h=32&w=32",
                "medium": "https://images.unsplash.com/profile-1590013010768-2c020b66411aimage?ixlib=rb-1.2.1&q=80&fm=jpg&crop=faces&cs=tinysrgb&fit=crop&h=64&w=64",
                "large": "https://images.unsplash.com/profile-1590013010768-2c020b66411aimage?ixlib=rb-1.2.1&q=80&fm=jpg&crop=faces&cs=tinysrgb&fit=crop&h=128&w=128"
            },
            "instagram_username": "jancantyphd",
            "total_collections": 14,
            "total_likes": 22,
            "total_photos": 697,
            "accepted_tos": true,
            "for_hire": false,
            "social": {
                "instagram_username": "jancantyphd",
                "portfolio_url": null,
                "twitter_username": null,
                "paypal_email": null
            }
        },
        "tags": [
            {
                "type": "search",
                "title": "arizona"
            },
            {
                "type": "search",
                "title": "page"
            },
            {
                "type": "search",
                "title": "usa"
            }
        ]
    },
    {
        "id": "wjxF3btvf7c",
        "created_at": "2019-09-06T14:01:55-04:00",
        "updated_at": "2021-12-11T22:07:21-05:00",
        "promoted_at": null,
        "width": 6000,
        "height": 4000,
        "color": "#0c8cd9",
        "blur_hash": "LZ7zlqaIbdbIF8o$e-bH#NV@j]js",
        "description": "Tolmie Peak lookout tower",
        "alt_description": "building on top of a mountain under blue sky during daytime",
        "urls": {
            "raw": "https://images.unsplash.com/photo-1567792712183-d91a965c3eb6?ixid=MnwyODE0NDJ8MHwxfHNlYXJjaHwyfHxkZWZpYW50fGVufDB8MHx8fDE2MzkzNTEyOTA&ixlib=rb-1.2.1",
            "full": "https://images.unsplash.com/photo-1567792712183-d91a965c3eb6?crop=entropy&cs=srgb&fm=jpg&ixid=MnwyODE0NDJ8MHwxfHNlYXJjaHwyfHxkZWZpYW50fGVufDB8MHx8fDE2MzkzNTEyOTA&ixlib=rb-1.2.1&q=85",
            "regular": "https://images.unsplash.com/photo-1567792712183-d91a965c3eb6?crop=entropy&cs=tinysrgb&fit=max&fm=jpg&ixid=MnwyODE0NDJ8MHwxfHNlYXJjaHwyfHxkZWZpYW50fGVufDB8MHx8fDE2MzkzNTEyOTA&ixlib=rb-1.2.1&q=80&w=1080",
            "small": "https://images.unsplash.com/photo-1567792712183-d91a965c3eb6?crop=entropy&cs=tinysrgb&fit=max&fm=jpg&ixid=MnwyODE0NDJ8MHwxfHNlYXJjaHwyfHxkZWZpYW50fGVufDB8MHx8fDE2MzkzNTEyOTA&ixlib=rb-1.2.1&q=80&w=400",
            "thumb": "https://images.unsplash.com/photo-1567792712183-d91a965c3eb6?crop=entropy&cs=tinysrgb&fit=max&fm=jpg&ixid=MnwyODE0NDJ8MHwxfHNlYXJjaHwyfHxkZWZpYW50fGVufDB8MHx8fDE2MzkzNTEyOTA&ixlib=rb-1.2.1&q=80&w=200"
        },
        "links": {
            "self": "https://api.unsplash.com/photos/wjxF3btvf7c",
            "html": "https://unsplash.com/photos/wjxF3btvf7c",
            "download": "https://unsplash.com/photos/wjxF3btvf7c/download?ixid=MnwyODE0NDJ8MHwxfHNlYXJjaHwyfHxkZWZpYW50fGVufDB8MHx8fDE2MzkzNTEyOTA",
            "download_location": "https://api.unsplash.com/photos/wjxF3btvf7c/download?ixid=MnwyODE0NDJ8MHwxfHNlYXJjaHwyfHxkZWZpYW50fGVufDB8MHx8fDE2MzkzNTEyOTA"
        },
        "categories": [],
        "likes": 40,
        "liked_by_user": false,
        "current_user_collections": [],
        "sponsorship": null,
        "topic_submissions": {},
        "user": {
            "id": "E9bBmwORDbM",
            "updated_at": "2021-12-09T10:54:50-05:00",
            "username": "inertkrypton",
            "name": "Jason Rost",
            "first_name": "Jason",
            "last_name": "Rost",
            "twitter_username": null,
            "portfolio_url": "https://www.jasonrost.com/photography",
            "bio": "Having spent two years exploring the world as an event photographer, primarily focusing on gaming and human interest, I’m on the lookout for new and exciting opportunities and will travel to realize them.\r\n\r\nIn need of a photographer? Get in touch!",
            "location": "Seattle, WA",
            "links": {
                "self": "https://api.unsplash.com/users/inertkrypton",
                "html": "https://unsplash.com/@inertkrypton",
                "photos": "https://api.unsplash.com/users/inertkrypton/photos",
                "likes": "https://api.unsplash.com/users/inertkrypton/likes",
                "portfolio": "https://api.unsplash.com/users/inertkrypton/portfolio",
                "following": "https://api.unsplash.com/users/inertkrypton/following",
                "followers": "https://api.unsplash.com/users/inertkrypton/followers"
            },
            "profile_image": {
                "small": "https://images.unsplash.com/profile-1564080169125-f5b3ad4f271b?ixlib=rb-1.2.1&q=80&fm=jpg&crop=faces&cs=tinysrgb&fit=crop&h=32&w=32",
                "medium": "https://images.unsplash.com/profile-1564080169125-f5b3ad4f271b?ixlib=rb-1.2.1&q=80&fm=jpg&crop=faces&cs=tinysrgb&fit=crop&h=64&w=64",
                "large": "https://images.unsplash.com/profile-1564080169125-f5b3ad4f271b?ixlib=rb-1.2.1&q=80&fm=jpg&crop=faces&cs=tinysrgb&fit=crop&h=128&w=128"
            },
            "instagram_username": "rostjason",
            "total_collections": 0,
            "total_likes": 33,
            "total_photos": 83,
            "accepted_tos": true,
            "for_hire": false,
            "social": {
                "instagram_username": "rostjason",
                "portfolio_url": "https://www.jasonrost.com/photography",
                "twitter_username": null,
                "paypal_email": null
            }
        },
        "tags": [
            {
                "type": "search",
                "title": "usa"
            },
            {
                "type": "search",
                "title": "tolmie peak"
            },
            {
                "type": "search",
                "title": "washington"
            }
        ]
    },
    {
        "id": "L9FXcgNwy4o",
        "created_at": "2020-09-25T20:53:33-04:00",
        "updated_at": "2021-12-12T00:13:49-05:00",
        "promoted_at": null,
        "width": 6000,
        "height": 4000,
        "color": "#404026",
        "blur_hash": "LSFO=R00xvIASPnht8V@9ZWX%2WW",
        "description": "Back Alley, Appleton",
        "alt_description": "blue metal gate near white concrete building during daytime",
        "urls": {
            "raw": "https://images.unsplash.com/photo-1601081485350-a7334a5d7be4?ixid=MnwyODE0NDJ8MHwxfHNlYXJjaHwzfHxkZWZpYW50fGVufDB8MHx8fDE2MzkzNTEyOTA&ixlib=rb-1.2.1",
            "full": "https://images.unsplash.com/photo-1601081485350-a7334a5d7be4?crop=entropy&cs=srgb&fm=jpg&ixid=MnwyODE0NDJ8MHwxfHNlYXJjaHwzfHxkZWZpYW50fGVufDB8MHx8fDE2MzkzNTEyOTA&ixlib=rb-1.2.1&q=85",
            "regular": "https://images.unsplash.com/photo-1601081485350-a7334a5d7be4?crop=entropy&cs=tinysrgb&fit=max&fm=jpg&ixid=MnwyODE0NDJ8MHwxfHNlYXJjaHwzfHxkZWZpYW50fGVufDB8MHx8fDE2MzkzNTEyOTA&ixlib=rb-1.2.1&q=80&w=1080",
            "small": "https://images.unsplash.com/photo-1601081485350-a7334a5d7be4?crop=entropy&cs=tinysrgb&fit=max&fm=jpg&ixid=MnwyODE0NDJ8MHwxfHNlYXJjaHwzfHxkZWZpYW50fGVufDB8MHx8fDE2MzkzNTEyOTA&ixlib=rb-1.2.1&q=80&w=400",
            "thumb": "https://images.unsplash.com/photo-1601081485350-a7334a5d7be4?crop=entropy&cs=tinysrgb&fit=max&fm=jpg&ixid=MnwyODE0NDJ8MHwxfHNlYXJjaHwzfHxkZWZpYW50fGVufDB8MHx8fDE2MzkzNTEyOTA&ixlib=rb-1.2.1&q=80&w=200"
        },
        "links": {
            "self": "https://api.unsplash.com/photos/L9FXcgNwy4o",
            "html": "https://unsplash.com/photos/L9FXcgNwy4o",
            "download": "https://unsplash.com/photos/L9FXcgNwy4o/download?ixid=MnwyODE0NDJ8MHwxfHNlYXJjaHwzfHxkZWZpYW50fGVufDB8MHx8fDE2MzkzNTEyOTA",
            "download_location": "https://api.unsplash.com/photos/L9FXcgNwy4o/download?ixid=MnwyODE0NDJ8MHwxfHNlYXJjaHwzfHxkZWZpYW50fGVufDB8MHx8fDE2MzkzNTEyOTA"
        },
        "categories": [],
        "likes": 1,
        "liked_by_user": false,
        "current_user_collections": [],
        "sponsorship": null,
        "topic_submissions": {},
        "user": {
            "id": "hviPTGS86vA",
            "updated_at": "2021-12-12T14:05:59-05:00",
            "username": "anakin1814",
            "name": "Gary Meulemans",
            "first_name": "Gary",
            "last_name": "Meulemans",
            "twitter_username": "anakin1814",
            "portfolio_url": null,
            "bio": null,
            "location": null,
            "links": {
                "self": "https://api.unsplash.com/users/anakin1814",
                "html": "https://unsplash.com/@anakin1814",
                "photos": "https://api.unsplash.com/users/anakin1814/photos",
                "likes": "https://api.unsplash.com/users/anakin1814/likes",
                "portfolio": "https://api.unsplash.com/users/anakin1814/portfolio",
                "following": "https://api.unsplash.com/users/anakin1814/following",
                "followers": "https://api.unsplash.com/users/anakin1814/followers"
            },
            "profile_image": {
                "small": "https://images.unsplash.com/profile-1631764390961-ea042d4099abimage?ixlib=rb-1.2.1&q=80&fm=jpg&crop=faces&cs=tinysrgb&fit=crop&h=32&w=32",
                "medium": "https://images.unsplash.com/profile-1631764390961-ea042d4099abimage?ixlib=rb-1.2.1&q=80&fm=jpg&crop=faces&cs=tinysrgb&fit=crop&h=64&w=64",
                "large": "https://images.unsplash.com/profile-1631764390961-ea042d4099abimage?ixlib=rb-1.2.1&q=80&fm=jpg&crop=faces&cs=tinysrgb&fit=crop&h=128&w=128"
            },
            "instagram_username": "anakin1814",
            "total_collections": 12,
            "total_likes": 10,
            "total_photos": 158,
            "accepted_tos": true,
            "for_hire": false,
            "social": {
                "instagram_username": "anakin1814",
                "portfolio_url": null,
                "twitter_username": "anakin1814",
                "paypal_email": null
            }
        },
        "tags": [
            {
                "type": "search",
                "title": "alley"
            },
            {
                "type": "search",
                "title": "shadows"
            },
            {
                "type": "landing_page",
                "title": " light",
                "source": {
                    "ancestry": {
                        "type": {
                            "slug": "backgrounds",
                            "pretty_slug": "Backgrounds"
                        },
                        "category": {
                            "slug": "colors",
                            "pretty_slug": "Colors"
                        },
                        "subcategory": {
                            "slug": "light",
                            "pretty_slug": "Light"
                        }
                    },
                    "title": "Light Backgrounds",
                    "subtitle": "Download free light background images",
                    "description": "Unsplash has an amazing collection of light backgrounds, covering all different shades and styles. Our images are professionally-shot, and you can use any/all of them for free!",
                    "meta_title": "900+ Light Background Images: Download HD Backgrounds on Unsplash",
                    "meta_description": "Choose from hundreds of free light backgrounds. Download beautiful, curated free backgrounds on Unsplash.",
                    "cover_photo": {
                        "id": "2x19-mRQgX8",
                        "created_at": "2016-12-19T11:23:39-05:00",
                        "updated_at": "2021-12-11T01:01:17-05:00",
                        "promoted_at": "2016-12-19T11:23:39-05:00",
                        "width": 5760,
                        "height": 3840,
                        "color": "#26260c",
                        "blur_hash": "LB8g4=R-0#WB=_WWNHWCE2ay={kC",
                        "description": null,
                        "alt_description": "person holding string lights",
                        "urls": {
                            "raw": "https://images.unsplash.com/photo-1482164565953-04b62dcac1cd?ixlib=rb-1.2.1",
                            "full": "https://images.unsplash.com/photo-1482164565953-04b62dcac1cd?ixlib=rb-1.2.1&q=85&fm=jpg&crop=entropy&cs=srgb",
                            "regular": "https://images.unsplash.com/photo-1482164565953-04b62dcac1cd?ixlib=rb-1.2.1&q=80&fm=jpg&crop=entropy&cs=tinysrgb&w=1080&fit=max",
                            "small": "https://images.unsplash.com/photo-1482164565953-04b62dcac1cd?ixlib=rb-1.2.1&q=80&fm=jpg&crop=entropy&cs=tinysrgb&w=400&fit=max",
                            "thumb": "https://images.unsplash.com/photo-1482164565953-04b62dcac1cd?ixlib=rb-1.2.1&q=80&fm=jpg&crop=entropy&cs=tinysrgb&w=200&fit=max"
                        },
                        "links": {
                            "self": "https://api.unsplash.com/photos/2x19-mRQgX8",
                            "html": "https://unsplash.com/photos/2x19-mRQgX8",
                            "download": "https://unsplash.com/photos/2x19-mRQgX8/download",
                            "download_location": "https://api.unsplash.com/photos/2x19-mRQgX8/download"
                        },
                        "categories": [],
                        "likes": 2005,
                        "liked_by_user": false,
                        "current_user_collections": [],
                        "sponsorship": null,
                        "topic_submissions": {
                            "spirituality": {
                                "status": "approved",
                                "approved_on": "2020-04-06T10:20:22-04:00"
                            }
                        },
                        "user": {
                            "id": "eoa2PWCTCbk",
                            "updated_at": "2021-12-11T10:24:29-05:00",
                            "username": "joshboot",
                            "name": "Josh Boot",
                            "first_name": "Josh",
                            "last_name": "Boot",
                            "twitter_username": "joshboot_",
                            "portfolio_url": "http://www.joshbootcreative.com",
                            "bio": "Photographer & Film-Maker from Sheffield that loves capturing light & beauty.",
                            "location": "Sheffield",
                            "links": {
                                "self": "https://api.unsplash.com/users/joshboot",
                                "html": "https://unsplash.com/@joshboot",
                                "photos": "https://api.unsplash.com/users/joshboot/photos",
                                "likes": "https://api.unsplash.com/users/joshboot/likes",
                                "portfolio": "https://api.unsplash.com/users/joshboot/portfolio",
                                "following": "https://api.unsplash.com/users/joshboot/following",
                                "followers": "https://api.unsplash.com/users/joshboot/followers"
                            },
                            "profile_image": {
                                "small": "https://images.unsplash.com/profile-1456313839517-8fda35d2f1e5?ixlib=rb-1.2.1&q=80&fm=jpg&crop=faces&cs=tinysrgb&fit=crop&h=32&w=32",
                                "medium": "https://images.unsplash.com/profile-1456313839517-8fda35d2f1e5?ixlib=rb-1.2.1&q=80&fm=jpg&crop=faces&cs=tinysrgb&fit=crop&h=64&w=64",
                                "large": "https://images.unsplash.com/profile-1456313839517-8fda35d2f1e5?ixlib=rb-1.2.1&q=80&fm=jpg&crop=faces&cs=tinysrgb&fit=crop&h=128&w=128"
                            },
                            "instagram_username": "joshboot",
                            "total_collections": 0,
                            "total_likes": 82,
                            "total_photos": 16,
                            "accepted_tos": true,
                            "for_hire": true,
                            "social": {
                                "instagram_username": "joshboot",
                                "portfolio_url": "http://www.joshbootcreative.com",
                                "twitter_username": "joshboot_",
                                "paypal_email": null
                            }
                        }
                    }
                }
            }
        ]
    }
]