[
    {
        "id": "-xoXlVmsH6I",
        "created_at": "2019-10-12T05:19:11-04:00",
        "updated_at": "2021-12-11T06:11:51-05:00",
        "promoted_at": null,
        "width": 8320,
        "height": 4677,
        "color": "#d9400c",
        "blur_hash": "LeIUny+vsmoLM|X8W;WW1{SzWBWV",
        "description": "A sledgehammer sits upright on a white line on an Orange interior track at a gym in Virginia. ",
        "alt_description": "black hedgehammer",
        "urls": {
            "raw": "https://images.unsplash.com/photo-1570871902031-ecde063f3fa0?ixid=MnwyODE0NDJ8MHwxfHNlYXJjaHwxfHxzdHJlbmd0aGVufGVufDB8MHx8fDE2MzkyODcyMjE&ixlib=rb-1.2.1",
            "full": "https://images.unsplash.com/photo-1570871902031-ecde063f3fa0?crop=entropy&cs=srgb&fm=jpg&ixid=MnwyODE0NDJ8MHwxfHNlYXJjaHwxfHxzdHJlbmd0aGVufGVufDB8MHx8fDE2MzkyODcyMjE&ixlib=rb-1.2.1&q=85",
            "regular": "https://images.unsplash.com/photo-1570871902031-ecde063f3fa0?crop=entropy&cs=tinysrgb&fit=max&fm=jpg&ixid=MnwyODE0NDJ8MHwxfHNlYXJjaHwxfHxzdHJlbmd0aGVufGVufDB8MHx8fDE2MzkyODcyMjE&ixlib=rb-1.2.1&q=80&w=1080",
            "small": "https://images.unsplash.com/photo-1570871902031-ecde063f3fa0?crop=entropy&cs=tinysrgb&fit=max&fm=jpg&ixid=MnwyODE0NDJ8MHwxfHNlYXJjaHwxfHxzdHJlbmd0aGVufGVufDB8MHx8fDE2MzkyODcyMjE&ixlib=rb-1.2.1&q=80&w=400",
            "thumb": "https://images.unsplash.com/photo-1570871902031-ecde063f3fa0?crop=entropy&cs=tinysrgb&fit=max&fm=jpg&ixid=MnwyODE0NDJ8MHwxfHNlYXJjaHwxfHxzdHJlbmd0aGVufGVufDB8MHx8fDE2MzkyODcyMjE&ixlib=rb-1.2.1&q=80&w=200"
        },
        "links": {
            "self": "https://api.unsplash.com/photos/-xoXlVmsH6I",
            "html": "https://unsplash.com/photos/-xoXlVmsH6I",
            "download": "https://unsplash.com/photos/-xoXlVmsH6I/download?ixid=MnwyODE0NDJ8MHwxfHNlYXJjaHwxfHxzdHJlbmd0aGVufGVufDB8MHx8fDE2MzkyODcyMjE",
            "download_location": "https://api.unsplash.com/photos/-xoXlVmsH6I/download?ixid=MnwyODE0NDJ8MHwxfHNlYXJjaHwxfHxzdHJlbmd0aGVufGVufDB8MHx8fDE2MzkyODcyMjE"
        },
        "categories": [],
        "likes": 8,
        "liked_by_user": false,
        "current_user_collections": [],
        "sponsorship": null,
        "topic_submissions": {
            "athletics": {
                "status": "approved",
                "approved_on": "2020-09-08T06:46:54-04:00"
            }
        },
        "user": {
            "id": "4lPs89CvYW0",
            "updated_at": "2021-12-11T22:11:20-05:00",
            "username": "thenewmalcolm",
            "name": "Obi Onyeador",
            "first_name": "Obi",
            "last_name": "Onyeador",
            "twitter_username": null,
            "portfolio_url": null,
            "bio": "Pixel 6 Pro",
            "location": "Fairfax Virginia",
            "links": {
                "self": "https://api.unsplash.com/users/thenewmalcolm",
                "html": "https://unsplash.com/@thenewmalcolm",
                "photos": "https://api.unsplash.com/users/thenewmalcolm/photos",
                "likes": "https://api.unsplash.com/users/thenewmalcolm/likes",
                "portfolio": "https://api.unsplash.com/users/thenewmalcolm/portfolio",
                "following": "https://api.unsplash.com/users/thenewmalcolm/following",
                "followers": "https://api.unsplash.com/users/thenewmalcolm/followers"
            },
            "profile_image": {
                "small": "https://images.unsplash.com/profile-1637622676005-78c320c4950aimage?ixlib=rb-1.2.1&q=80&fm=jpg&crop=faces&cs=tinysrgb&fit=crop&h=32&w=32",
                "medium": "https://images.unsplash.com/profile-1637622676005-78c320c4950aimage?ixlib=rb-1.2.1&q=80&fm=jpg&crop=faces&cs=tinysrgb&fit=crop&h=64&w=64",
                "large": "https://images.unsplash.com/profile-1637622676005-78c320c4950aimage?ixlib=rb-1.2.1&q=80&fm=jpg&crop=faces&cs=tinysrgb&fit=crop&h=128&w=128"
            },
            "instagram_username": "upgradeur_life",
            "total_collections": 45,
            "total_likes": 3,
            "total_photos": 205,
            "accepted_tos": true,
            "for_hire": true,
            "social": {
                "instagram_username": "upgradeur_life",
                "portfolio_url": null,
                "twitter_username": null,
                "paypal_email": null
            }
        },
        "tags": [
            {
                "type": "landing_page",
                "title": "red",
                "source": {
                    "ancestry": {
                        "type": {
                            "slug": "wallpapers",
                            "pretty_slug": "HD Wallpapers"
                        },
                        "category": {
                            "slug": "colors",
                            "pretty_slug": "Color"
                        },
                        "subcategory": {
                            "slug": "red",
                            "pretty_slug": "Red"
                        }
                    },
                    "title": "HD Red Wallpapers",
                    "subtitle": "Download Free Red Wallpapers",
                    "description": "Choose from a curated selection of red wallpapers for your mobile and desktop screens. Always free on Unsplash.",
                    "meta_title": "Red Wallpapers: Free HD Download [500+ HQ] | Unsplash",
                    "meta_description": "Choose from hundreds of free red wallpapers. Download HD wallpapers for free on Unsplash.",
                    "cover_photo": {
                        "id": "HyBXy5PHQR8",
                        "created_at": "2018-02-17T13:44:58-05:00",
                        "updated_at": "2021-12-10T03:04:04-05:00",
                        "promoted_at": null,
                        "width": 3024,
                        "height": 4032,
                        "color": "#400c0c",
                        "blur_hash": "L9Bmx_o1o1Jl|cwxWpWpN]$5N]sU",
                        "description": null,
                        "alt_description": "red textile",
                        "urls": {
                            "raw": "https://images.unsplash.com/photo-1518893063132-36e46dbe2428?ixlib=rb-1.2.1",
                            "full": "https://images.unsplash.com/photo-1518893063132-36e46dbe2428?ixlib=rb-1.2.1&q=85&fm=jpg&crop=entropy&cs=srgb",
                            "regular": "https://images.unsplash.com/photo-1518893063132-36e46dbe2428?ixlib=rb-1.2.1&q=80&fm=jpg&crop=entropy&cs=tinysrgb&w=1080&fit=max",
                            "small": "https://images.unsplash.com/photo-1518893063132-36e46dbe2428?ixlib=rb-1.2.1&q=80&fm=jpg&crop=entropy&cs=tinysrgb&w=400&fit=max",
                            "thumb": "https://images.unsplash.com/photo-1518893063132-36e46dbe2428?ixlib=rb-1.2.1&q=80&fm=jpg&crop=entropy&cs=tinysrgb&w=200&fit=max"
                        },
                        "links": {
                            "self": "https://api.unsplash.com/photos/HyBXy5PHQR8",
                            "html": "https://unsplash.com/photos/HyBXy5PHQR8",
                            "download": "https://unsplash.com/photos/HyBXy5PHQR8/download",
                            "download_location": "https://api.unsplash.com/photos/HyBXy5PHQR8/download"
                        },
                        "categories": [],
                        "likes": 2089,
                        "liked_by_user": false,
                        "current_user_collections": [],
                        "sponsorship": null,
                        "topic_submissions": {
                            "textures-patterns": {
                                "status": "approved",
                                "approved_on": "2020-06-12T09:15:09-04:00"
                            }
                        },
                        "user": {
                            "id": "6nkkrwW9M-s",
                            "updated_at": "2021-12-10T08:58:40-05:00",
                            "username": "montylov",
                            "name": "MontyLov",
                            "first_name": "MontyLov",
                            "last_name": null,
                            "twitter_username": "MontyLov",
                            "portfolio_url": "http://montylov.com",
                            "bio": "Stay humble and innovate.",
                            "location": null,
                            "links": {
                                "self": "https://api.unsplash.com/users/montylov",
                                "html": "https://unsplash.com/@montylov",
                                "photos": "https://api.unsplash.com/users/montylov/photos",
                                "likes": "https://api.unsplash.com/users/montylov/likes",
                                "portfolio": "https://api.unsplash.com/users/montylov/portfolio",
                                "following": "https://api.unsplash.com/users/montylov/following",
                                "followers": "https://api.unsplash.com/users/montylov/followers"
                            },
                            "profile_image": {
                                "small": "https://images.unsplash.com/profile-1588478301600-b5e5203a574aimage?ixlib=rb-1.2.1&q=80&fm=jpg&crop=faces&cs=tinysrgb&fit=crop&h=32&w=32",
                                "medium": "https://images.unsplash.com/profile-1588478301600-b5e5203a574aimage?ixlib=rb-1.2.1&q=80&fm=jpg&crop=faces&cs=tinysrgb&fit=crop&h=64&w=64",
                                "large": "https://images.unsplash.com/profile-1588478301600-b5e5203a574aimage?ixlib=rb-1.2.1&q=80&fm=jpg&crop=faces&cs=tinysrgb&fit=crop&h=128&w=128"
                            },
                            "instagram_username": "montylov",
                            "total_collections": 1,
                            "total_likes": 0,
                            "total_photos": 79,
                            "accepted_tos": false,
                            "for_hire": false,
                            "social": {
                                "instagram_username": "montylov",
                                "portfolio_url": "http://montylov.com",
                                "twitter_username": "MontyLov",
                                "paypal_email": null
                            }
                        }
                    }
                }
            },
            {
                "type": "search",
                "title": "smoke pipe"
            },
            {
                "type": "search",
                "title": "handrail"
            }
        ]
    },
    {
        "id": "KDJ1TbLDoOo",
        "created_at": "2021-05-27T07:49:14-04:00",
        "updated_at": "2021-12-11T02:28:01-05:00",
        "promoted_at": null,
        "width": 5582,
        "height": 3140,
        "color": "#f3f3f3",
        "blur_hash": "LdQmVJbG~Cxu-ps;I:M{xaWBIos;",
        "description": "Refreshing",
        "alt_description": "listerine cool mint mouth wash",
        "urls": {
            "raw": "https://images.unsplash.com/photo-1622115914441-fe73c383673d?ixid=MnwyODE0NDJ8MHwxfHNlYXJjaHwyfHxzdHJlbmd0aGVufGVufDB8MHx8fDE2MzkyODcyMjE&ixlib=rb-1.2.1",
            "full": "https://images.unsplash.com/photo-1622115914441-fe73c383673d?crop=entropy&cs=srgb&fm=jpg&ixid=MnwyODE0NDJ8MHwxfHNlYXJjaHwyfHxzdHJlbmd0aGVufGVufDB8MHx8fDE2MzkyODcyMjE&ixlib=rb-1.2.1&q=85",
            "regular": "https://images.unsplash.com/photo-1622115914441-fe73c383673d?crop=entropy&cs=tinysrgb&fit=max&fm=jpg&ixid=MnwyODE0NDJ8MHwxfHNlYXJjaHwyfHxzdHJlbmd0aGVufGVufDB8MHx8fDE2MzkyODcyMjE&ixlib=rb-1.2.1&q=80&w=1080",
            "small": "https://images.unsplash.com/photo-1622115914441-fe73c383673d?crop=entropy&cs=tinysrgb&fit=max&fm=jpg&ixid=MnwyODE0NDJ8MHwxfHNlYXJjaHwyfHxzdHJlbmd0aGVufGVufDB8MHx8fDE2MzkyODcyMjE&ixlib=rb-1.2.1&q=80&w=400",
            "thumb": "https://images.unsplash.com/photo-1622115914441-fe73c383673d?crop=entropy&cs=tinysrgb&fit=max&fm=jpg&ixid=MnwyODE0NDJ8MHwxfHNlYXJjaHwyfHxzdHJlbmd0aGVufGVufDB8MHx8fDE2MzkyODcyMjE&ixlib=rb-1.2.1&q=80&w=200"
        },
        "links": {
            "self": "https://api.unsplash.com/photos/KDJ1TbLDoOo",
            "html": "https://unsplash.com/photos/KDJ1TbLDoOo",
            "download": "https://unsplash.com/photos/KDJ1TbLDoOo/download?ixid=MnwyODE0NDJ8MHwxfHNlYXJjaHwyfHxzdHJlbmd0aGVufGVufDB8MHx8fDE2MzkyODcyMjE",
            "download_location": "https://api.unsplash.com/photos/KDJ1TbLDoOo/download?ixid=MnwyODE0NDJ8MHwxfHNlYXJjaHwyfHxzdHJlbmd0aGVufGVufDB8MHx8fDE2MzkyODcyMjE"
        },
        "categories": [],
        "likes": 5,
        "liked_by_user": false,
        "current_user_collections": [],
        "sponsorship": null,
        "topic_submissions": {},
        "user": {
            "id": "Hz7Jneqps7c",
            "updated_at": "2021-12-11T18:49:47-05:00",
            "username": "mishaalzahed",
            "name": "Mishaal Zahed",
            "first_name": "Mishaal",
            "last_name": "Zahed",
            "twitter_username": "mishaalzahed",
            "portfolio_url": "https://pin.it/1eFgTtK",
            "bio": "Asalamualaykum",
            "location": "Riyadh, KSA",
            "links": {
                "self": "https://api.unsplash.com/users/mishaalzahed",
                "html": "https://unsplash.com/@mishaalzahed",
                "photos": "https://api.unsplash.com/users/mishaalzahed/photos",
                "likes": "https://api.unsplash.com/users/mishaalzahed/likes",
                "portfolio": "https://api.unsplash.com/users/mishaalzahed/portfolio",
                "following": "https://api.unsplash.com/users/mishaalzahed/following",
                "followers": "https://api.unsplash.com/users/mishaalzahed/followers"
            },
            "profile_image": {
                "small": "https://images.unsplash.com/profile-1631835735131-dc7d08becbc5image?ixlib=rb-1.2.1&q=80&fm=jpg&crop=faces&cs=tinysrgb&fit=crop&h=32&w=32",
                "medium": "https://images.unsplash.com/profile-1631835735131-dc7d08becbc5image?ixlib=rb-1.2.1&q=80&fm=jpg&crop=faces&cs=tinysrgb&fit=crop&h=64&w=64",
                "large": "https://images.unsplash.com/profile-1631835735131-dc7d08becbc5image?ixlib=rb-1.2.1&q=80&fm=jpg&crop=faces&cs=tinysrgb&fit=crop&h=128&w=128"
            },
            "instagram_username": null,
            "total_collections": 3,
            "total_likes": 2192,
            "total_photos": 359,
            "accepted_tos": true,
            "for_hire": true,
            "social": {
                "instagram_username": null,
                "portfolio_url": "https://pin.it/1eFgTtK",
                "twitter_username": "mishaalzahed",
                "paypal_email": null
            }
        },
        "tags": [
            {
                "type": "search",
                "title": "mishaal zahed"
            },
            {
                "type": "search",
                "title": "listerine"
            },
            {
                "type": "search",
                "title": "fight"
            }
        ]
    }
]