[
    {
        "id": "owBcefxgrIE",
        "created_at": "2018-03-14T21:07:02-04:00",
        "updated_at": "2021-12-28T01:02:36-05:00",
        "promoted_at": null,
        "width": 5150,
        "height": 4016,
        "color": "#262626",
        "blur_hash": "LOA-SHVXtSyERPkDMwWB8wkXkCMw",
        "description": "I received a call from the school nurse, who put my son on the line. My son told me he was very sad and was feeling depressed. I immediately went to my son’s school to pick him up. Before we left, we met with one of the administrators, who helped my son feel a little better. \r\n\r\nThe whole afternoon I couldn’t stop thinking about how sad my son was when I arrived at the school. A few hours later, when I went upstairs for some quiet time, it hit me that my son may be depressed…just like me.\r\n\r\nWhat I love about this image is the raw emotion that shows just how hard parenting can be sometimes.",
        "alt_description": "person crying beside bed",
        "urls": {
            "raw": "https://images.unsplash.com/photo-1521075486433-bf4052bb37bc?ixid=MnwyODE0NDJ8MHwxfHNlYXJjaHwxfHx0ZWFyZnVsfGVufDB8MHx8fDE2NDA3MzA2MjU&ixlib=rb-1.2.1",
            "full": "https://images.unsplash.com/photo-1521075486433-bf4052bb37bc?crop=entropy&cs=srgb&fm=jpg&ixid=MnwyODE0NDJ8MHwxfHNlYXJjaHwxfHx0ZWFyZnVsfGVufDB8MHx8fDE2NDA3MzA2MjU&ixlib=rb-1.2.1&q=85",
            "regular": "https://images.unsplash.com/photo-1521075486433-bf4052bb37bc?crop=entropy&cs=tinysrgb&fit=max&fm=jpg&ixid=MnwyODE0NDJ8MHwxfHNlYXJjaHwxfHx0ZWFyZnVsfGVufDB8MHx8fDE2NDA3MzA2MjU&ixlib=rb-1.2.1&q=80&w=1080",
            "small": "https://images.unsplash.com/photo-1521075486433-bf4052bb37bc?crop=entropy&cs=tinysrgb&fit=max&fm=jpg&ixid=MnwyODE0NDJ8MHwxfHNlYXJjaHwxfHx0ZWFyZnVsfGVufDB8MHx8fDE2NDA3MzA2MjU&ixlib=rb-1.2.1&q=80&w=400",
            "thumb": "https://images.unsplash.com/photo-1521075486433-bf4052bb37bc?crop=entropy&cs=tinysrgb&fit=max&fm=jpg&ixid=MnwyODE0NDJ8MHwxfHNlYXJjaHwxfHx0ZWFyZnVsfGVufDB8MHx8fDE2NDA3MzA2MjU&ixlib=rb-1.2.1&q=80&w=200"
        },
        "links": {
            "self": "https://api.unsplash.com/photos/owBcefxgrIE",
            "html": "https://unsplash.com/photos/owBcefxgrIE",
            "download": "https://unsplash.com/photos/owBcefxgrIE/download?ixid=MnwyODE0NDJ8MHwxfHNlYXJjaHwxfHx0ZWFyZnVsfGVufDB8MHx8fDE2NDA3MzA2MjU",
            "download_location": "https://api.unsplash.com/photos/owBcefxgrIE/download?ixid=MnwyODE0NDJ8MHwxfHNlYXJjaHwxfHx0ZWFyZnVsfGVufDB8MHx8fDE2NDA3MzA2MjU"
        },
        "categories": [],
        "likes": 1087,
        "liked_by_user": false,
        "current_user_collections": [],
        "sponsorship": null,
        "topic_submissions": {},
        "user": {
            "id": "ql0bD1lI8fg",
            "updated_at": "2021-12-28T15:46:30-05:00",
            "username": "kaimantha",
            "name": "Claudia Wolff",
            "first_name": "Claudia",
            "last_name": "Wolff",
            "twitter_username": "hellowallflower",
            "portfolio_url": "http://www.wallflowerphotographer.com",
            "bio": "I'm a perpetually moody photographer and writer who loves anything moody and that makes me think. ",
            "location": "Charlotte, NC",
            "links": {
                "self": "https://api.unsplash.com/users/kaimantha",
                "html": "https://unsplash.com/@kaimantha",
                "photos": "https://api.unsplash.com/users/kaimantha/photos",
                "likes": "https://api.unsplash.com/users/kaimantha/likes",
                "portfolio": "https://api.unsplash.com/users/kaimantha/portfolio",
                "following": "https://api.unsplash.com/users/kaimantha/following",
                "followers": "https://api.unsplash.com/users/kaimantha/followers"
            },
            "profile_image": {
                "small": "https://images.unsplash.com/profile-1520469063738-54f3abf224c5?ixlib=rb-1.2.1&q=80&fm=jpg&crop=faces&cs=tinysrgb&fit=crop&h=32&w=32",
                "medium": "https://images.unsplash.com/profile-1520469063738-54f3abf224c5?ixlib=rb-1.2.1&q=80&fm=jpg&crop=faces&cs=tinysrgb&fit=crop&h=64&w=64",
                "large": "https://images.unsplash.com/profile-1520469063738-54f3abf224c5?ixlib=rb-1.2.1&q=80&fm=jpg&crop=faces&cs=tinysrgb&fit=crop&h=128&w=128"
            },
            "instagram_username": "ceeceewolff",
            "total_collections": 0,
            "total_likes": 173,
            "total_photos": 11,
            "accepted_tos": false,
            "for_hire": true,
            "social": {
                "instagram_username": "ceeceewolff",
                "portfolio_url": "http://www.wallflowerphotographer.com",
                "twitter_username": "hellowallflower",
                "paypal_email": null
            }
        },
        "tags": [
            {
                "type": "search",
                "title": "depression"
            },
            {
                "type": "search",
                "title": "crying"
            },
            {
                "type": "landing_page",
                "title": "woman",
                "source": {
                    "ancestry": {
                        "type": {
                            "slug": "images",
                            "pretty_slug": "Images"
                        },
                        "category": {
                            "slug": "people",
                            "pretty_slug": "People"
                        },
                        "subcategory": {
                            "slug": "women",
                            "pretty_slug": "Women"
                        }
                    },
                    "title": "Women Images & Pictures",
                    "subtitle": "Download free women images",
                    "description": "Choose from a curated selection of women photos. Always free on Unsplash.",
                    "meta_title": "Women Pictures | Download Free Images & Stock Photos on Unsplash",
                    "meta_description": "Choose from hundreds of free women pictures. Download HD women photos for free on Unsplash.",
                    "cover_photo": {
                        "id": "7-gtkXm2b5U",
                        "created_at": "2018-04-01T18:18:53-04:00",
                        "updated_at": "2021-04-27T23:01:34-04:00",
                        "promoted_at": "2018-04-03T23:36:45-04:00",
                        "width": 4000,
                        "height": 6016,
                        "color": "#0c2626",
                        "blur_hash": "LdG*]5Nb?Hn$E1s.InWX0KWBNGj[",
                        "description": null,
                        "alt_description": "woman hug each other",
                        "urls": {
                            "raw": "https://images.unsplash.com/photo-1522621032211-ac0031dfbddc?ixlib=rb-1.2.1",
                            "full": "https://images.unsplash.com/photo-1522621032211-ac0031dfbddc?ixlib=rb-1.2.1&q=85&fm=jpg&crop=entropy&cs=srgb",
                            "regular": "https://images.unsplash.com/photo-1522621032211-ac0031dfbddc?ixlib=rb-1.2.1&q=80&fm=jpg&crop=entropy&cs=tinysrgb&w=1080&fit=max",
                            "small": "https://images.unsplash.com/photo-1522621032211-ac0031dfbddc?ixlib=rb-1.2.1&q=80&fm=jpg&crop=entropy&cs=tinysrgb&w=400&fit=max",
                            "thumb": "https://images.unsplash.com/photo-1522621032211-ac0031dfbddc?ixlib=rb-1.2.1&q=80&fm=jpg&crop=entropy&cs=tinysrgb&w=200&fit=max"
                        },
                        "links": {
                            "self": "https://api.unsplash.com/photos/7-gtkXm2b5U",
                            "html": "https://unsplash.com/photos/7-gtkXm2b5U",
                            "download": "https://unsplash.com/photos/7-gtkXm2b5U/download",
                            "download_location": "https://api.unsplash.com/photos/7-gtkXm2b5U/download"
                        },
                        "categories": [],
                        "likes": 1875,
                        "liked_by_user": false,
                        "current_user_collections": [],
                        "sponsorship": null,
                        "topic_submissions": {
                            "people": {
                                "status": "approved",
                                "approved_on": "2020-04-06T10:20:24-04:00"
                            }
                        },
                        "user": {
                            "id": "puqDmqs-ols",
                            "updated_at": "2021-06-29T03:27:56-04:00",
                            "username": "holliver_1119678_sink",
                            "name": "Hian Oliveira",
                            "first_name": "Hian",
                            "last_name": "Oliveira",
                            "twitter_username": "agaiaene",
                            "portfolio_url": null,
                            "bio": null,
                            "location": null,
                            "links": {
                                "self": "https://api.unsplash.com/users/holliver_1119678_sink",
                                "html": "https://unsplash.com/@holliver_1119678_sink",
                                "photos": "https://api.unsplash.com/users/holliver_1119678_sink/photos",
                                "likes": "https://api.unsplash.com/users/holliver_1119678_sink/likes",
                                "portfolio": "https://api.unsplash.com/users/holliver_1119678_sink/portfolio",
                                "following": "https://api.unsplash.com/users/holliver_1119678_sink/following",
                                "followers": "https://api.unsplash.com/users/holliver_1119678_sink/followers"
                            },
                            "profile_image": {
                                "small": "https://images.unsplash.com/profile-1562479559774-86c3e75df43f?ixlib=rb-1.2.1&q=80&fm=jpg&crop=faces&cs=tinysrgb&fit=crop&h=32&w=32",
                                "medium": "https://images.unsplash.com/profile-1562479559774-86c3e75df43f?ixlib=rb-1.2.1&q=80&fm=jpg&crop=faces&cs=tinysrgb&fit=crop&h=64&w=64",
                                "large": "https://images.unsplash.com/profile-1562479559774-86c3e75df43f?ixlib=rb-1.2.1&q=80&fm=jpg&crop=faces&cs=tinysrgb&fit=crop&h=128&w=128"
                            },
                            "instagram_username": "h.olliver",
                            "total_collections": 1,
                            "total_likes": 153,
                            "total_photos": 0,
                            "accepted_tos": true,
                            "for_hire": true,
                            "social": {
                                "instagram_username": "h.olliver",
                                "portfolio_url": null,
                                "twitter_username": "agaiaene",
                                "paypal_email": null
                            }
                        }
                    }
                }
            }
        ]
    },
    {
        "id": "7I1wrtRz5QQ",
        "created_at": "2018-01-21T20:41:22-05:00",
        "updated_at": "2021-12-27T13:02:49-05:00",
        "promoted_at": null,
        "width": 7360,
        "height": 4912,
        "color": "#262626",
        "blur_hash": "L46[2H_34n00M{IUIUIUofj[%M-;",
        "description": "A honest look at the pain of mental illness.",
        "alt_description": "grayscale photo of woman crying holding her right chest",
        "urls": {
            "raw": "https://images.unsplash.com/photo-1516585142943-4341daf22d5f?ixid=MnwyODE0NDJ8MHwxfHNlYXJjaHwyfHx0ZWFyZnVsfGVufDB8MHx8fDE2NDA3MzA2MjU&ixlib=rb-1.2.1",
            "full": "https://images.unsplash.com/photo-1516585142943-4341daf22d5f?crop=entropy&cs=srgb&fm=jpg&ixid=MnwyODE0NDJ8MHwxfHNlYXJjaHwyfHx0ZWFyZnVsfGVufDB8MHx8fDE2NDA3MzA2MjU&ixlib=rb-1.2.1&q=85",
            "regular": "https://images.unsplash.com/photo-1516585142943-4341daf22d5f?crop=entropy&cs=tinysrgb&fit=max&fm=jpg&ixid=MnwyODE0NDJ8MHwxfHNlYXJjaHwyfHx0ZWFyZnVsfGVufDB8MHx8fDE2NDA3MzA2MjU&ixlib=rb-1.2.1&q=80&w=1080",
            "small": "https://images.unsplash.com/photo-1516585142943-4341daf22d5f?crop=entropy&cs=tinysrgb&fit=max&fm=jpg&ixid=MnwyODE0NDJ8MHwxfHNlYXJjaHwyfHx0ZWFyZnVsfGVufDB8MHx8fDE2NDA3MzA2MjU&ixlib=rb-1.2.1&q=80&w=400",
            "thumb": "https://images.unsplash.com/photo-1516585142943-4341daf22d5f?crop=entropy&cs=tinysrgb&fit=max&fm=jpg&ixid=MnwyODE0NDJ8MHwxfHNlYXJjaHwyfHx0ZWFyZnVsfGVufDB8MHx8fDE2NDA3MzA2MjU&ixlib=rb-1.2.1&q=80&w=200"
        },
        "links": {
            "self": "https://api.unsplash.com/photos/7I1wrtRz5QQ",
            "html": "https://unsplash.com/photos/7I1wrtRz5QQ",
            "download": "https://unsplash.com/photos/7I1wrtRz5QQ/download?ixid=MnwyODE0NDJ8MHwxfHNlYXJjaHwyfHx0ZWFyZnVsfGVufDB8MHx8fDE2NDA3MzA2MjU",
            "download_location": "https://api.unsplash.com/photos/7I1wrtRz5QQ/download?ixid=MnwyODE0NDJ8MHwxfHNlYXJjaHwyfHx0ZWFyZnVsfGVufDB8MHx8fDE2NDA3MzA2MjU"
        },
        "categories": [],
        "likes": 1231,
        "liked_by_user": false,
        "current_user_collections": [],
        "sponsorship": null,
        "topic_submissions": {},
        "user": {
            "id": "sB1EijB_4-U",
            "updated_at": "2021-12-28T16:56:28-05:00",
            "username": "kj2018",
            "name": "Kat J",
            "first_name": "Kat",
            "last_name": "J",
            "twitter_username": null,
            "portfolio_url": null,
            "bio": null,
            "location": null,
            "links": {
                "self": "https://api.unsplash.com/users/kj2018",
                "html": "https://unsplash.com/@kj2018",
                "photos": "https://api.unsplash.com/users/kj2018/photos",
                "likes": "https://api.unsplash.com/users/kj2018/likes",
                "portfolio": "https://api.unsplash.com/users/kj2018/portfolio",
                "following": "https://api.unsplash.com/users/kj2018/following",
                "followers": "https://api.unsplash.com/users/kj2018/followers"
            },
            "profile_image": {
                "small": "https://images.unsplash.com/profile-1516588733076-4f35e403d4ef?ixlib=rb-1.2.1&q=80&fm=jpg&crop=faces&cs=tinysrgb&fit=crop&h=32&w=32",
                "medium": "https://images.unsplash.com/profile-1516588733076-4f35e403d4ef?ixlib=rb-1.2.1&q=80&fm=jpg&crop=faces&cs=tinysrgb&fit=crop&h=64&w=64",
                "large": "https://images.unsplash.com/profile-1516588733076-4f35e403d4ef?ixlib=rb-1.2.1&q=80&fm=jpg&crop=faces&cs=tinysrgb&fit=crop&h=128&w=128"
            },
            "instagram_username": "boohaifarm",
            "total_collections": 5,
            "total_likes": 59,
            "total_photos": 3,
            "accepted_tos": false,
            "for_hire": false,
            "social": {
                "instagram_username": "boohaifarm",
                "portfolio_url": null,
                "twitter_username": null,
                "paypal_email": null
            }
        },
        "tags": [
            {
                "type": "search",
                "title": "depression"
            },
            {
                "type": "search",
                "title": "face"
            },
            {
                "type": "landing_page",
                "title": "people",
                "source": {
                    "ancestry": {
                        "type": {
                            "slug": "images",
                            "pretty_slug": "Images"
                        },
                        "category": {
                            "slug": "people",
                            "pretty_slug": "People"
                        }
                    },
                    "title": "People Images & Pictures",
                    "subtitle": "Download free people images",
                    "description": "Human faces speak to us in a way that language cannot. Everyone recognize a smile, a frown, tears. Unsplash has the finest selection of people images on the web: high-def and curated for quality. Family, friends, men, women, Unsplash has photos for all.",
                    "meta_title": "People Pictures [HQ] | Download Free Images on Unsplash",
                    "meta_description": "Choose from hundreds of free people pictures. Download HD people photos for free on Unsplash.",
                    "cover_photo": {
                        "id": "PmNjS6b3XP4",
                        "created_at": "2017-04-20T18:04:07-04:00",
                        "updated_at": "2021-12-21T14:45:44-05:00",
                        "promoted_at": "2017-04-21T12:00:49-04:00",
                        "width": 4630,
                        "height": 3087,
                        "color": "#a6d9d9",
                        "blur_hash": "LjI=x%:QUbv#NHWVa}kCt7jFjZfQ",
                        "description": "Summer in France with baby",
                        "alt_description": "woman carrying baby while walking",
                        "urls": {
                            "raw": "https://images.unsplash.com/photo-1492725764893-90b379c2b6e7?ixlib=rb-1.2.1",
                            "full": "https://images.unsplash.com/photo-1492725764893-90b379c2b6e7?ixlib=rb-1.2.1&q=85&fm=jpg&crop=entropy&cs=srgb",
                            "regular": "https://images.unsplash.com/photo-1492725764893-90b379c2b6e7?ixlib=rb-1.2.1&q=80&fm=jpg&crop=entropy&cs=tinysrgb&w=1080&fit=max",
                            "small": "https://images.unsplash.com/photo-1492725764893-90b379c2b6e7?ixlib=rb-1.2.1&q=80&fm=jpg&crop=entropy&cs=tinysrgb&w=400&fit=max",
                            "thumb": "https://images.unsplash.com/photo-1492725764893-90b379c2b6e7?ixlib=rb-1.2.1&q=80&fm=jpg&crop=entropy&cs=tinysrgb&w=200&fit=max"
                        },
                        "links": {
                            "self": "https://api.unsplash.com/photos/PmNjS6b3XP4",
                            "html": "https://unsplash.com/photos/PmNjS6b3XP4",
                            "download": "https://unsplash.com/photos/PmNjS6b3XP4/download",
                            "download_location": "https://api.unsplash.com/photos/PmNjS6b3XP4/download"
                        },
                        "categories": [],
                        "likes": 2358,
                        "liked_by_user": false,
                        "current_user_collections": [],
                        "sponsorship": null,
                        "topic_submissions": {
                            "current-events": {
                                "status": "approved",
                                "approved_on": "2021-03-01T07:52:57-05:00"
                            }
                        },
                        "user": {
                            "id": "7S_pCRiCiQo",
                            "updated_at": "2021-12-21T12:15:27-05:00",
                            "username": "thedakotacorbin",
                            "name": "Dakota Corbin",
                            "first_name": "Dakota",
                            "last_name": "Corbin",
                            "twitter_username": "thedakotacorbin",
                            "portfolio_url": null,
                            "bio": "Husband | Father | Creator",
                            "location": "Utah, United States",
                            "links": {
                                "self": "https://api.unsplash.com/users/thedakotacorbin",
                                "html": "https://unsplash.com/@thedakotacorbin",
                                "photos": "https://api.unsplash.com/users/thedakotacorbin/photos",
                                "likes": "https://api.unsplash.com/users/thedakotacorbin/likes",
                                "portfolio": "https://api.unsplash.com/users/thedakotacorbin/portfolio",
                                "following": "https://api.unsplash.com/users/thedakotacorbin/following",
                                "followers": "https://api.unsplash.com/users/thedakotacorbin/followers"
                            },
                            "profile_image": {
                                "small": "https://images.unsplash.com/profile-1623795199834-f8109281554dimage?ixlib=rb-1.2.1&q=80&fm=jpg&crop=faces&cs=tinysrgb&fit=crop&h=32&w=32",
                                "medium": "https://images.unsplash.com/profile-1623795199834-f8109281554dimage?ixlib=rb-1.2.1&q=80&fm=jpg&crop=faces&cs=tinysrgb&fit=crop&h=64&w=64",
                                "large": "https://images.unsplash.com/profile-1623795199834-f8109281554dimage?ixlib=rb-1.2.1&q=80&fm=jpg&crop=faces&cs=tinysrgb&fit=crop&h=128&w=128"
                            },
                            "instagram_username": "thedakotacorbin",
                            "total_collections": 0,
                            "total_likes": 1,
                            "total_photos": 44,
                            "accepted_tos": true,
                            "for_hire": true,
                            "social": {
                                "instagram_username": "thedakotacorbin",
                                "portfolio_url": null,
                                "twitter_username": "thedakotacorbin",
                                "paypal_email": null
                            }
                        }
                    }
                }
            }
        ]
    }
]